[
    {
        "id": "Burger01",
        "name": "Veg Burger",
        "image": "Veg Burger.avif",
        "price": "79"
    },
    {
        "id": "Burger04",
        "name": "Aloo Tikki Burger",
        "image": "Aloo Tikki Burger.avif",
        "price": "99"
    },
    {
        "id": "Burger02",
        "name": "Cheese Burger",
        "image": "Cheese Burger.avif",
        "price": "120" 
    },
    {
        "id": "Burger03",
        "name": "Paneer Cheese Burger",
        "image": "Paneer Cheese Burger.avif",
        "price": "139" 
    }
   
]